MANIFEST.in
README.rst
setup.py
bob/__init__.py
bob.db.maskattack.egg-info/PKG-INFO
bob.db.maskattack.egg-info/SOURCES.txt
bob.db.maskattack.egg-info/dependency_links.txt
bob.db.maskattack.egg-info/entry_points.txt
bob.db.maskattack.egg-info/not-zip-safe
bob.db.maskattack.egg-info/requires.txt
bob.db.maskattack.egg-info/top_level.txt
bob/db/__init__.py
bob/db/maskattack/__init__.py
bob/db/maskattack/checkfiles.py
bob/db/maskattack/create.py
bob/db/maskattack/db.sql3
bob/db/maskattack/driver.py
bob/db/maskattack/dumplist.py
bob/db/maskattack/models.py
bob/db/maskattack/query.py
bob/db/maskattack/test.py
bob/db/maskattack/scripts/__init__.py
bob/db/maskattack/scripts/make_color_videos.py